{
  "id": 4917,
  "recolorToFind": [
    8741,
    25238,
    6798,
    7700,
    11200
  ],
  "anInt2156": 32,
  "name": "Trobert",
  "recolorToReplace": [
    12,
    127,
    12,
    7083,
    111
  ],
  "models": [
    235,
    246,
    292,
    254,
    323,
    179,
    185,
    151,
    290,
    518,
    326
  ],
  "models_2": [
    67
  ],
  "stanceAnimation": 808,
  "anInt2165": -1,
  "tileSpacesOccupied": 1,
  "walkAnimation": 819,
  "rotate90RightAnimation": 821,
  "aBool2170": true,
  "resizeX": 128,
  "contrast": 0,
  "rotate180Animation": 820,
  "anInt2174": -1,
  "options": [
    "Talk-to",
    null,
    null,
    null,
    null
  ],
  "renderOnMinimap": true,
  "combatLevel": 0,
  "rotate90LeftAnimation": 822,
  "resizeY": 128,
  "hasRenderPriority": false,
  "ambient": 0,
  "headIcon": -1,
  "anInt2184": 30,
  "anInt2187": -1,
  "isClickable": true,
  "anInt2189": -1,
  "aBool2190": false
}