{
  "id": 667,
  "recolorToFind": [
    6331,
    6323,
    12060,
    11941
  ],
  "anInt2156": 32,
  "name": "Goblin",
  "recolorToReplace": [
    22414,
    22410,
    9891,
    9767
  ],
  "models": [
    24435,
    24441,
    24452,
    24455,
    24472,
    24485,
    24509
  ],
  "models_2": [
    24209
  ],
  "stanceAnimation": 6186,
  "anInt2165": -1,
  "tileSpacesOccupied": 1,
  "walkAnimation": 6187,
  "rotate90RightAnimation": -1,
  "aBool2170": true,
  "resizeX": 130,
  "contrast": 0,
  "rotate180Animation": -1,
  "anInt2174": -1,
  "options": [
    "Talk-to",
    "Attack",
    null,
    null,
    null
  ],
  "renderOnMinimap": true,
  "combatLevel": 5,
  "rotate90LeftAnimation": -1,
  "resizeY": 130,
  "hasRenderPriority": false,
  "ambient": 15,
  "headIcon": -1,
  "anInt2184": 30,
  "anInt2187": -1,
  "isClickable": true,
  "anInt2189": -1,
  "aBool2190": false
}