{
  "id": 1101,
  "anInt2156": 32,
  "name": "Giant Sea Snake",
  "models": [
    15096
  ],
  "stanceAnimation": 4037,
  "anInt2165": -1,
  "tileSpacesOccupied": 5,
  "walkAnimation": 4037,
  "rotate90RightAnimation": -1,
  "aBool2170": true,
  "resizeX": 71,
  "contrast": 0,
  "rotate180Animation": -1,
  "anInt2174": -1,
  "options": [
    null,
    "Attack",
    null,
    null,
    null
  ],
  "renderOnMinimap": true,
  "combatLevel": 149,
  "rotate90LeftAnimation": -1,
  "resizeY": 71,
  "hasRenderPriority": true,
  "ambient": 10,
  "headIcon": -1,
  "anInt2184": 30,
  "anInt2187": -1,
  "isClickable": true,
  "anInt2189": -1,
  "aBool2190": false
}