{
  "id": 6354,
  "recolorToFind": [
    0,
    910,
    912,
    1938,
    1814,
    1690
  ],
  "anInt2156": 32,
  "name": "Chronozon",
  "recolorToReplace": [
    1577,
    2962,
    2964,
    1942,
    1944,
    1946
  ],
  "models": [
    17375,
    17391,
    17384,
    17399
  ],
  "stanceAnimation": 66,
  "anInt2165": -1,
  "tileSpacesOccupied": 3,
  "walkAnimation": 63,
  "rotate90RightAnimation": -1,
  "aBool2170": true,
  "resizeX": 110,
  "contrast": 0,
  "rotate180Animation": -1,
  "anInt2174": -1,
  "options": [
    null,
    "Attack",
    null,
    null,
    null
  ],
  "renderOnMinimap": true,
  "combatLevel": 170,
  "rotate90LeftAnimation": -1,
  "resizeY": 110,
  "hasRenderPriority": true,
  "ambient": 0,
  "headIcon": -1,
  "anInt2184": 30,
  "anInt2187": -1,
  "isClickable": true,
  "anInt2189": -1,
  "aBool2190": false
}