{
  "It's coming home": [
    {
      "It's coming home": 1,
      "It's coming home": 2349,
      "It's coming home": "It's coming home",
      "It's coming home": 6.3
    },
    {
      "It's coming home": 1,
      "It's coming home": 1351,
      "It's coming home": "It's coming home",
      "It's coming home": 12.5
    },
    {
      "It's coming home": 1,
      "It's coming home": 1205,
      "It's coming home": "It's coming home",
      "It's coming home": 12.5
    },
    {
      "It's coming home": 2,
      "It's coming home": 1422,
      "It's coming home": "It's coming home",
      "It's coming home": 12.5
    },
    {
      "It's coming home": 3,
      "It's coming home": 1139,
      "It's coming home": "It's coming home",
      "It's coming home": 12.5
    },
    {
      "It's coming home": 3,
      "It's coming home": 9375,
      "It's coming home": "It's coming home",
      "It's coming home": 12.5
    },
    {
      "It's coming home": 4,
      "It's coming home": 4819,
      "It's coming home": "It's coming home",
      "It's coming home": 12.5
    },
    {
      "It's coming home": 4,
      "It's coming home": 1277,
      "It's coming home": "It's coming home",
      "It's coming home": 12.5
    },
    {
      "It's coming home": 4,
      "It's coming home": 1794,
      "It's coming home": "It's coming home",
      "It's coming home": 12.5
    },
    {
      "It's coming home": 4,
      "It's coming home": 819,
      "It's coming home": "It's coming home",
      "It's coming home": 12.5
    },
    {
      "It's coming home": 5,
      "It's coming home": 39,
      "It's coming home": "It's coming home",
      "It's coming home": 12.5
    },
    {
      "It's coming home": 5,
      "It's coming home": 1321,
      "It's coming home": "It's coming home",
      "It's coming home": 25
    },
    {
      "It's coming home": 6,
      "It's coming home": 19570,
      "It's coming home": "It's coming home",
      "It's coming home": 12.5
    },
    {
      "It's coming home": 6,
      "It's coming home": 1291,
      "It's coming home": "It's coming home",
      "It's coming home": 25
    },
    {
      "It's coming home": 6,
      "It's coming home": 9420,
      "It's coming home": "It's coming home",
      "It's coming home": 12.5
    },
    {
      "It's coming home": 7,
      "It's coming home": 864,
      "It's coming home": "It's coming home",
      "It's coming home": 12.5
    },
    {
      "It's coming home": 7,
      "It's coming home": 1155,
      "It's coming home": "It's coming home",
      "It's coming home": 25
    },
    {
      "It's coming home": 8,
      "It's coming home": 1173,
      "It's coming home": "It's coming home",
      "It's coming home": 25
    },
    {
      "It's coming home": 9,
      "It's coming home": 1337,
      "It's coming home": "It's coming home",
      "It's coming home": 37.5
    },
    {
      "It's coming home": 10,
      "It's coming home": 1375,
      "It's coming home": "It's coming home",
      "It's coming home": 37.5
    },
    {
      "It's coming home": 11,
      "It's coming home": 1103,
      "It's coming home": "It's coming home",
      "It's coming home": 37.5
    },
    {
      "It's coming home": 12,
      "It's coming home": 1189,
      "It's coming home": "It's coming home",
      "It's coming home": 37.5
    },
    {
      "It's coming home": 13,
      "It's coming home": 3095,
      "It's coming home": "It's coming home",
      "It's coming home": 25
    },
    {
      "It's coming home": 14,
      "It's coming home": 1307,
      "It's coming home": "It's coming home",
      "It's coming home": 37.5
    },
    {
      "It's coming home": 15,
      "It's coming home": 2351,
      "It's coming home": "It's coming home",
      "It's coming home": 12.5
    },
    {
      "It's coming home": 15,
      "It's coming home": 1203,
      "It's coming home": "It's coming home",
      "It's coming home": 25
    },
    {
      "It's coming home": 16,
      "It's coming home": 1349,
      "It's coming home": "It's coming home",
      "It's coming home": 25
    },
    {
      "It's coming home": 16,
      "It's coming home": 1075,
      "It's coming home": "It's coming home",
      "It's coming home": 37.5
    },
    {
      "It's coming home": 16,
      "It's coming home": 1087,
      "It's coming home": "It's coming home",
      "It's coming home": 37.5
    },
    {
      "It's coming home": 17,
      "It's coming home": 7225,
      "It's coming home": "It's coming home",
      "It's coming home": 25
    },
    {
      "It's coming home": 17,
      "It's coming home": 1420,
      "It's coming home": "It's coming home",
      "It's coming home": 25
    },
    {
      "It's coming home": 18,
      "It's coming home": 9377,
      "It's coming home": "It's coming home",
      "It's coming home": 25
    },
    {
      "It's coming home": 18,
      "It's coming home": 1117,
      "It's coming home": "It's coming home",
      "It's coming home": 62.5
    },
    {
      "It's coming home": 18,
      "It's coming home": 1137,
      "It's coming home": "It's coming home",
      "It's coming home": 25
    },
    {
      "It's coming home": 19,
      "It's coming home": 4820,
      "It's coming home": "It's coming home",
      "It's coming home": 25
    },
    {
      "It's coming home": 19,
      "It's coming home": 820,
      "It's coming home": "It's coming home",
      "It's coming home": 25
    },
    {
      "It's coming home": 19,
      "It's coming home": 1279,
      "It's coming home": "It's coming home",
      "It's coming home": 25
    },
    {
      "It's coming home": 20,
      "It's coming home": 2355,
      "It's coming home": "It's coming home",
      "It's coming home": 13.7
    },
    {
      "It's coming home": 20,
      "It's coming home": 40,
      "It's coming home": "It's coming home",
      "It's coming home": 25
    },
    {
      "It's coming home": 20,
      "It's coming home": 1323,
      "It's coming home": "It's coming home",
      "It's coming home": 50
    },
    {
      "It's coming home": 21,
      "It's coming home": 1293,
      "It's coming home": "It's coming home",
      "It's coming home": 50
    },
    {
      "It's coming home": 21,
      "It's coming home": 19572,
      "It's coming home": "It's coming home",
      "It's coming home": 25
    },
    {
      "It's coming home": 22,
      "It's coming home": 1153,
      "It's coming home": "It's coming home",
      "It's coming home": 50
    },
    {
      "It's coming home": 22,
      "It's coming home": 863,
      "It's coming home": "It's coming home",
      "It's coming home": 25
    },
    {
      "It's coming home": 23,
      "It's coming home": 9423,
      "It's coming home": "It's coming home",
      "It's coming home": 25
    },
    {
      "It's coming home": 23,
      "It's coming home": 1175,
      "It's coming home": "It's coming home",
      "It's coming home": 50
    },
    {
      "It's coming home": 24,
      "It's coming home": 1335,
      "It's coming home": "It's coming home",
      "It's coming home": 75
    },
    {
      "It's coming home": 25,
      "It's coming home": 1363,
      "It's coming home": "It's coming home",
      "It's coming home": 75
    },
    {
      "It's coming home": 26,
      "It's coming home": 4540,
      "It's coming home": "It's coming home",
      "It's coming home": 25
    },
    {
      "It's coming home": 26,
      "It's coming home": 1101,
      "It's coming home": "It's coming home",
      "It's coming home": 75
    },
    {
      "It's coming home": 27,
      "It's coming home": 1191,
      "It's coming home": "It's coming home",
      "It's coming home": 75
    },
    {
      "It's coming home": 28,
      "It's coming home": 3096,
      "It's coming home": "It's coming home",
      "It's coming home": 50
    },
    {
      "It's coming home": 29,
      "It's coming home": 1309,
      "It's coming home": "It's coming home",
      "It's coming home": 75
    },
    {
      "It's coming home": 30,
      "It's coming home": 2353,
      "It's coming home": "It's coming home",
      "It's coming home": 17.5
    },
    {
      "It's coming home": 30,
      "It's coming home": 1207,
      "It's coming home": "It's coming home",
      "It's coming home": 27
    },
    {
      "It's coming home": 30,
      "It's coming home": 2353,
      "It's coming home": "It's coming home",
      "It's coming home": 17.5
    },
    {
      "It's coming home": 31,
      "It's coming home": 1081,
      "It's coming home": "It's coming home",
      "It's coming home": 75
    },
    {
      "It's coming home": 31,
      "It's coming home": 1067,
      "It's coming home": "It's coming home",
      "It's coming home": 75
    },
    {
      "It's coming home": 31,
      "It's coming home": 1353,
      "It's coming home": "It's coming home",
      "It's coming home": 37
    },
    {
      "It's coming home": 32,
      "It's coming home": 1424,
      "It's coming home": "It's coming home",
      "It's coming home": 37
    },
    {
      "It's coming home": 33,
      "It's coming home": 1115,
      "It's coming home": "It's coming home",
      "It's coming home": 125
    },
    {
      "It's coming home": 33,
      "It's coming home": 1141,
      "It's coming home": "It's coming home",
      "It's coming home": 37
    },
    {
      "It's coming home": 33,
      "It's coming home": 9378,
      "It's coming home": "It's coming home",
      "It's coming home": 37
    },
    {
      "It's coming home": 34,
      "It's coming home": 821,
      "It's coming home": "It's coming home",
      "It's coming home": 37
    },
    {
      "It's coming home": 34,
      "It's coming home": 1539,
      "It's coming home": "It's coming home",
      "It's coming home": 37
    },
    {
      "It's coming home": 34,
      "It's coming home": 1281,
      "It's coming home": "It's coming home",
      "It's coming home": 37
    },
    {
      "It's coming home": 35,
      "It's coming home": 2,
      "It's coming home": "It's coming home",
      "It's coming home": 25.6
    },
    {
      "It's coming home": 35,
      "It's coming home": 1325,
      "It's coming home": "It's coming home",
      "It's coming home": 75
    },
    {
      "It's coming home": 35,
      "It's coming home": 41,
      "It's coming home": "It's coming home",
      "It's coming home": 37
    },
    {
      "It's coming home": 36,
      "It's coming home": 9425,
      "It's coming home": "It's coming home",
      "It's coming home": 37
    },
    {
      "It's coming home": 36,
      "It's coming home": 2370,
      "It's coming home": "It's coming home",
      "It's coming home": 37
    },
    {
      "It's coming home": 36,
      "It's coming home": 1295,
      "It's coming home": "It's coming home",
      "It's coming home": 75
    },
    {
      "It's coming home": 36,
      "It's coming home": 19574,
      "It's coming home": "It's coming home",
      "It's coming home": 37.5
    },
    {
      "It's coming home": 37,
      "It's coming home": 865,
      "It's coming home": "It's coming home",
      "It's coming home": 37.5
    },
    {
      "It's coming home": 37,
      "It's coming home": 1157,
      "It's coming home": "It's coming home",
      "It's coming home": 75
    },
    {
      "It's coming home": 38,
      "It's coming home": 1177,
      "It's coming home": "It's coming home",
      "It's coming home": 75
    },
    {
      "It's coming home": 39,
      "It's coming home": 1339,
      "It's coming home": "It's coming home",
      "It's coming home": 112
    },
    {
      "It's coming home": 40,
      "It's coming home": 1365,
      "It's coming home": "It's coming home",
      "It's coming home": 112
    },
    {
      "It's coming home": 40,
      "It's coming home": 2357,
      "It's coming home": "It's coming home",
      "It's coming home": 56.2
    },
    {
      "It's coming home": 40,
      "It's coming home": 2357,
      "It's coming home": "It's coming home",
      "It's coming home": 22.5
    },
    {
      "It's coming home": 41,
      "It's coming home": 1105,
      "It's coming home": "It's coming home",
      "It's coming home": 112
    },
    {
      "It's coming home": 42,
      "It's coming home": 1193,
      "It's coming home": "It's coming home",
      "It's coming home": 112
    },
    {
      "It's coming home": 43,
      "It's coming home": 3097,
      "It's coming home": "It's coming home",
      "It's coming home": 75
    },
    {
      "It's coming home": 44,
      "It's coming home": 1311,
      "It's coming home": "It's coming home",
      "It's coming home": 112
    },
    {
      "It's coming home": 46,
      "It's coming home": 1069,
      "It's coming home": "It's coming home",
      "It's coming home": 112
    },
    {
      "It's coming home": 46,
      "It's coming home": 1083,
      "It's coming home": "It's coming home",
      "It's coming home": 112
    },
    {
      "It's coming home": 48,
      "It's coming home": 1119,
      "It's coming home": "It's coming home",
      "It's coming home": 187.5
    },
    {
      "It's coming home": 49,
      "It's coming home": 4544,
      "It's coming home": "It's coming home",
      "It's coming home": 37
    },
    {
      "It's coming home": 50,
      "It's coming home": 1209,
      "It's coming home": "It's coming home",
      "It's coming home": 50
    },
    {
      "It's coming home": 50,
      "It's coming home": 2359,
      "It's coming home": "It's coming home",
      "It's coming home": 30
    },
    {
      "It's coming home": 50,
      "It's coming home": 2359,
      "It's coming home": "It's coming home",
      "It's coming home": 30
    },
    {
      "It's coming home": 51,
      "It's coming home": 1355,
      "It's coming home": "It's coming home",
      "It's coming home": 50
    },
    {
      "It's coming home": 52,
      "It's coming home": 1428,
      "It's coming home": "It's coming home",
      "It's coming home": 50
    },
    {
      "It's coming home": 53,
      "It's coming home": 1143,
      "It's coming home": "It's coming home",
      "It's coming home": 50
    },
    {
      "It's coming home": 53,
      "It's coming home": 9379,
      "It's coming home": "It's coming home",
      "It's coming home": 50
    },
    {
      "It's coming home": 54,
      "It's coming home": 1285,
      "It's coming home": "It's coming home",
      "It's coming home": 50
    },
    {
      "It's coming home": 54,
      "It's coming home": 822,
      "It's coming home": "It's coming home",
      "It's coming home": 50
    },
    {
      "It's coming home": 54,
      "It's coming home": 4822,
      "It's coming home": "It's coming home",
      "It's coming home": 50
    },
    {
      "It's coming home": 55,
      "It's coming home": 42,
      "It's coming home": "It's coming home",
      "It's coming home": 50
    },
    {
      "It's coming home": 55,
      "It's coming home": 1329,
      "It's coming home": "It's coming home",
      "It's coming home": 100
    },
    {
      "It's coming home": 56,
      "It's coming home": 1299,
      "It's coming home": "It's coming home",
      "It's coming home": 100
    },
    {
      "It's coming home": 56,
      "It's coming home": 19576,
      "It's coming home": "It's coming home",
      "It's coming home": 50
    },
    {
      "It's coming home": 56,
      "It's coming home": 9427,
      "It's coming home": "It's coming home",
      "It's coming home": 50
    },
    {
      "It's coming home": 57,
      "It's coming home": 1159,
      "It's coming home": "It's coming home",
      "It's coming home": 100
    },
    {
      "It's coming home": 57,
      "It's coming home": 866,
      "It's coming home": "It's coming home",
      "It's coming home": 50
    },
    {
      "It's coming home": 58,
      "It's coming home": 1181,
      "It's coming home": "It's coming home",
      "It's coming home": 100
    },
    {
      "It's coming home": 59,
      "It's coming home": 9416,
      "It's coming home": "It's coming home",
      "It's coming home": 50
    },
    {
      "It's coming home": 59,
      "It's coming home": 1343,
      "It's coming home": "It's coming home",
      "It's coming home": 150
    },
    {
      "It's coming home": 60,
      "It's coming home": 1187,
      "It's coming home": "It's coming home",
      "It's coming home": 75
    },
    {
      "It's coming home": 60,
      "It's coming home": 1369,
      "It's coming home": "It's coming home",
      "It's coming home": 150
    },
    {
      "It's coming home": 61,
      "It's coming home": 1109,
      "It's coming home": "It's coming home",
      "It's coming home": 150
    },
    {
      "It's coming home": 62,
      "It's coming home": 1197,
      "It's coming home": "It's coming home",
      "It's coming home": 150
    },
    {
      "It's coming home": 63,
      "It's coming home": 3099,
      "It's coming home": "It's coming home",
      "It's coming home": 100
    },
    {
      "It's coming home": 64,
      "It's coming home": 1315,
      "It's coming home": "It's coming home",
      "It's coming home": 150
    },
    {
      "It's coming home": 66,
      "It's coming home": 1085,
      "It's coming home": "It's coming home",
      "It's coming home": 150
    },
    {
      "It's coming home": 66,
      "It's coming home": 1071,
      "It's coming home": "It's coming home",
      "It's coming home": 150
    },
    {
      "It's coming home": 68,
      "It's coming home": 1121,
      "It's coming home": "It's coming home",
      "It's coming home": 250
    },
    {
      "It's coming home": 70,
      "It's coming home": 2361,
      "It's coming home": "It's coming home",
      "It's coming home": 37.5
    },
    {
      "It's coming home": 70,
      "It's coming home": 1211,
      "It's coming home": "It's coming home",
      "It's coming home": 62.5
    },
    {
      "It's coming home": 70,
      "It's coming home": 2361,
      "It's coming home": "It's coming home",
      "It's coming home": 37.5
    },
    {
      "It's coming home": 71,
      "It's coming home": 1357,
      "It's coming home": "It's coming home",
      "It's coming home": 62.5
    },
    {
      "It's coming home": 72,
      "It's coming home": 1430,
      "It's coming home": "It's coming home",
      "It's coming home": 62.5
    },
    {
      "It's coming home": 73,
      "It's coming home": 9380,
      "It's coming home": "It's coming home",
      "It's coming home": 62.5
    },
    {
      "It's coming home": 73,
      "It's coming home": 1145,
      "It's coming home": "It's coming home",
      "It's coming home": 62.5
    },
    {
      "It's coming home": 74,
      "It's coming home": 823,
      "It's coming home": "It's coming home",
      "It's coming home": 62.5
    },
    {
      "It's coming home": 74,
      "It's coming home": 1287,
      "It's coming home": "It's coming home",
      "It's coming home": 62.5
    },
    {
      "It's coming home": 74,
      "It's coming home": 4823,
      "It's coming home": "It's coming home",
      "It's coming home": 62.5
    },
    {
      "It's coming home": 75,
      "It's coming home": 43,
      "It's coming home": "It's coming home",
      "It's coming home": 62.5
    },
    {
      "It's coming home": 75,
      "It's coming home": 1331,
      "It's coming home": "It's coming home",
      "It's coming home": 125
    },
    {
      "It's coming home": 76,
      "It's coming home": 9429,
      "It's coming home": "It's coming home",
      "It's coming home": 62.5
    },
    {
      "It's coming home": 76,
      "It's coming home": 1301,
      "It's coming home": "It's coming home",
      "It's coming home": 125
    },
    {
      "It's coming home": 76,
      "It's coming home": 19578,
      "It's coming home": "It's coming home",
      "It's coming home": 62.5
    },
    {
      "It's coming home": 77,
      "It's coming home": 1161,
      "It's coming home": "It's coming home",
      "It's coming home": 125
    },
    {
      "It's coming home": 77,
      "It's coming home": 867,
      "It's coming home": "It's coming home",
      "It's coming home": 62.5
    },
    {
      "It's coming home": 78,
      "It's coming home": 1183,
      "It's coming home": "It's coming home",
      "It's coming home": 125
    },
    {
      "It's coming home": 79,
      "It's coming home": 1345,
      "It's coming home": "It's coming home",
      "It's coming home": 187.5
    },
    {
      "It's coming home": 80,
      "It's coming home": 1371,
      "It's coming home": "It's coming home",
      "It's coming home": 187.5
    },
    {
      "It's coming home": 81,
      "It's coming home": 1111,
      "It's coming home": "It's coming home",
      "It's coming home": 187.5
    },
    {
      "It's coming home": 82,
      "It's coming home": 1199,
      "It's coming home": "It's coming home",
      "It's coming home": 187.5
    },
    {
      "It's coming home": 83,
      "It's coming home": 3100,
      "It's coming home": "It's coming home",
      "It's coming home": 125
    },
    {
      "It's coming home": 84,
      "It's coming home": 1317,
      "It's coming home": "It's coming home",
      "It's coming home": 187.5
    },
    {
      "It's coming home": 85,
      "It's coming home": 2363,
      "It's coming home": "It's coming home",
      "It's coming home": 50
    },
    {
      "It's coming home": 85,
      "It's coming home": 2363,
      "It's coming home": "It's coming home",
      "It's coming home": 50
    },
    {
      "It's coming home": 85,
      "It's coming home": 1213,
      "It's coming home": "It's coming home",
      "It's coming home": 75
    },
    {
      "It's coming home": 86,
      "It's coming home": 1359,
      "It's coming home": "It's coming home",
      "It's coming home": 75
    },
    {
      "It's coming home": 86,
      "It's coming home": 1091,
      "It's coming home": "It's coming home",
      "It's coming home": 187.5
    },
    {
      "It's coming home": 86,
      "It's coming home": 1073,
      "It's coming home": "It's coming home",
      "It's coming home": 187.5
    },
    {
      "It's coming home": 87,
      "It's coming home": 1432,
      "It's coming home": "It's coming home",
      "It's coming home": 75
    },
    {
      "It's coming home": 88,
      "It's coming home": 9381,
      "It's coming home": "It's coming home",
      "It's coming home": 75
    },
    {
      "It's coming home": 88,
      "It's coming home": 1147,
      "It's coming home": "It's coming home",
      "It's coming home": 75
    },
    {
      "It's coming home": 88,
      "It's coming home": 1123,
      "It's coming home": "It's coming home",
      "It's coming home": 312
    },
    {
      "It's coming home": 89,
      "It's coming home": 1289,
      "It's coming home": "It's coming home",
      "It's coming home": 75
    },
    {
      "It's coming home": 89,
      "It's coming home": 4824,
      "It's coming home": "It's coming home",
      "It's coming home": 75
    },
    {
      "It's coming home": 89,
      "It's coming home": 824,
      "It's coming home": "It's coming home",
      "It's coming home": 75
    },
    {
      "It's coming home": 90,
      "It's coming home": 44,
      "It's coming home": "It's coming home",
      "It's coming home": 75
    },
    {
      "It's coming home": 90,
      "It's coming home": 1333,
      "It's coming home": "It's coming home",
      "It's coming home": 150
    },
    {
      "It's coming home": 90,
      "It's coming home": 11283,
      "It's coming home": "It's coming home",
      "It's coming home": 2000
    },
    {
      "It's coming home": 91,
      "It's coming home": 1303,
      "It's coming home": "It's coming home",
      "It's coming home": 150
    },
    {
      "It's coming home": 91,
      "It's coming home": 19580,
      "It's coming home": "It's coming home",
      "It's coming home": 75
    },
    {
      "It's coming home": 91,
      "It's coming home": 9431,
      "It's coming home": "It's coming home",
      "It's coming home": 75
    },
    {
      "It's coming home": 92,
      "It's coming home": 868,
      "It's coming home": "It's coming home",
      "It's coming home": 75
    },
    {
      "It's coming home": 92,
      "It's coming home": 1163,
      "It's coming home": "It's coming home",
      "It's coming home": 150
    },
    {
      "It's coming home": 93,
      "It's coming home": 1185,
      "It's coming home": "It's coming home",
      "It's coming home": 150
    },
    {
      "It's coming home": 94,
      "It's coming home": 1347,
      "It's coming home": "It's coming home",
      "It's coming home": 225
    },
    {
      "It's coming home": 95,
      "It's coming home": 1373,
      "It's coming home": "It's coming home",
      "It's coming home": 225
    },
    {
      "It's coming home": 96,
      "It's coming home": 1113,
      "It's coming home": "It's coming home",
      "It's coming home": 225
    },
    {
      "It's coming home": 97,
      "It's coming home": 1201,
      "It's coming home": "It's coming home",
      "It's coming home": 225
    },
    {
      "It's coming home": 98,
      "It's coming home": 3101,
      "It's coming home": "It's coming home",
      "It's coming home": 150
    },
    {
      "It's coming home": 99,
      "It's coming home": 1127,
      "It's coming home": "It's coming home",
      "It's coming home": 375
    },
    {
      "It's coming home": 99,
      "It's coming home": 1093,
      "It's coming home": "It's coming home",
      "It's coming home": 225
    },
    {
      "It's coming home": 99,
      "It's coming home": 1079,
      "It's coming home": "It's coming home",
      "It's coming home": 225
    },
    {
      "It's coming home": 99,
      "It's coming home": 1319,
      "It's coming home": "It's coming home",
      "It's coming home": 225
    }
  ]
}